LICENSE
loss_landscape_anim/__init__.py
loss_landscape_anim/_plot.py
loss_landscape_anim/datamodule.py
loss_landscape_anim/loss_landscape.py
loss_landscape_anim/main.py
loss_landscape_anim/model.py
loss_landscape_anim/sample_data/spirals.p
loss_landscape_anim-0.1.10.dist-info/LICENSE
loss_landscape_anim-0.1.10.dist-info/METADATA
loss_landscape_anim-0.1.10.dist-info/WHEEL
loss_landscape_anim-0.1.10.dist-info/RECORD
