Metadata-Version: 2.1
Name: loss-landscape-anim
Version: 0.1.10
Summary: Animate the optimization trajectory of neural networks
Home-page: https://github.com/logancyang/loss-landscape-anim
License: MIT
Keywords: pytorch,loss_landscape,pytorch_lightning,deep_learning,visualization
Author: LoganYang
Author-email: logancyang@gmail.com
Requires-Python: >=3.9,<4.0
Classifier: License :: OSI Approved :: MIT License
Classifier: Programming Language :: Python :: 3
Classifier: Programming Language :: Python :: 3.9
Classifier: Programming Language :: Python :: 3.10
Classifier: Programming Language :: Python :: 3.11
Classifier: Programming Language :: Python :: 3.12
Requires-Dist: importlib_resources (>=6.1.1,<7.0.0)
Requires-Dist: matplotlib (>=3.8.2,<4.0.0)
Requires-Dist: numpy (>=1.26.3,<2.0.0)
Requires-Dist: pytorch-lightning (>=2.1.3,<3.0.0)
Requires-Dist: scikit-learn (>=1.4.0,<2.0.0)
Requires-Dist: torch (>=2.1.2,<3.0.0)
Requires-Dist: torchvision (>=0.16.2,<0.17.0)
Requires-Dist: tqdm (>=4.66.1,<5.0.0)
Project-URL: Repository, https://github.com/logancyang/loss-landscape-anim
